Metadata-Version: 2.4
Name: hatchback
Version: 0.1.5
Summary: A CLI to generate a FastAPI + Alembic + SQLAlchemy boilerplate
Author: Ignacio Bares
License: Apache-2.0
Project-URL: Homepage, https://github.com/nachovoss/hatchback
Project-URL: Source, https://github.com/nachovoss/hatchback
Project-URL: Tracker, https://github.com/nachovoss/hatchback/issues
Keywords: fastapi-boilerplate,fastapi-cli,sqlalchemy-2,production-ready-api,pydantic-v2,alembic,docker,clean-architecture,rest-api,project-generator,scaffold,asyncio,jwt-auth,postgresql
Classifier: Programming Language :: Python :: 3
Classifier: License :: OSI Approved :: Apache Software License
Classifier: Operating System :: OS Independent
Requires-Python: >=3.8
License-File: LICENSE
Requires-Dist: rich
Dynamic: author
Dynamic: classifier
Dynamic: description
Dynamic: description-content-type
Dynamic: keywords
Dynamic: license
Dynamic: license-file
Dynamic: project-url
Dynamic: requires-dist
Dynamic: requires-python
Dynamic: summary
